ChangeLog
LICENSE.txt
README.rst
docs/Makefile
docs/conf.py
docs/index.rst
docs/make.bat
docs/requirements.txt
docs/_build/html/_modules/parmap/parmap.html
docs/_build/html/_sources/index.rst.txt
parmap/__init__.py
parmap/parmap.py
parmap-1.7.0.dist-info/METADATA
parmap-1.7.0.dist-info/WHEEL
parmap-1.7.0.dist-info/licenses/LICENSE.txt
parmap-1.7.0.dist-info/RECORD
