Metadata-Version: 2.1
Name: parmap
Version: 1.7.0
Summary: map and starmap implementations passing additional arguments and parallelizing if possible
Project-URL: Homepage, https://github.com/zeehio/parmap
Project-URL: Bug Tracker, https://github.com/zeehio/parmap/issues
Author-email: Sergio Oller <sergioller@gmail.com>
License-Expression: Apache-2.0
License-File: LICENSE.txt
Classifier: Development Status :: 5 - Production/Stable
Classifier: Intended Audience :: Developers
Classifier: License :: OSI Approved :: Apache Software License
Classifier: Operating System :: OS Independent
Classifier: Programming Language :: Python
Classifier: Programming Language :: Python :: 3
Classifier: Programming Language :: Python :: 3.8
Classifier: Programming Language :: Python :: 3.9
Classifier: Programming Language :: Python :: 3.10
Classifier: Programming Language :: Python :: 3.11
Provides-Extra: progress-bar
Requires-Dist: tqdm>=4.8.4; extra == 'progress-bar'
